yuxin_helpers/__init__.py
yuxin_helpers/colors.py
yuxin_helpers-0.1.6.dist-info/METADATA
yuxin_helpers-0.1.6.dist-info/WHEEL
yuxin_helpers-0.1.6.dist-info/top_level.txt
yuxin_helpers-0.1.6.dist-info/RECORD
