Metadata-Version: 2.1
Name: yuxin_helpers
Version: 0.1.6
Summary: Yuxin's helper package with utilities for diverse tasks.
Home-page: https://github.com/yuxingeng/yuxin_helpers
Author: Yuxin Geng
Author-email: yuxin.evol@gmail.com
Classifier: Programming Language :: Python :: 3
Classifier: License :: OSI Approved :: MIT License
Classifier: Operating System :: OS Independent
Requires-Python: >=3.6
Requires-Dist: matplotlib
Requires-Dist: numpy
